sinapsis_huggingface_transformers/__init__.py
sinapsis_huggingface_transformers/helpers/__init__.py
sinapsis_huggingface_transformers/helpers/tags.py
sinapsis_huggingface_transformers/helpers/text_to_sentences.py
sinapsis_huggingface_transformers/templates/__init__.py
sinapsis_huggingface_transformers/templates/base_transformers.py
sinapsis_huggingface_transformers/templates/image_to_text_transformers.py
sinapsis_huggingface_transformers/templates/speech_to_text_transformers.py
sinapsis_huggingface_transformers/templates/summarization_transformers.py
sinapsis_huggingface_transformers/templates/text_to_speech_transformers.py
sinapsis_huggingface_transformers/templates/translation_transformers.py
sinapsis_huggingface_transformers/templates/pali_gemma/pali_gemma_base.py
sinapsis_huggingface_transformers/templates/pali_gemma/pali_gemma_detection.py
sinapsis_huggingface_transformers/templates/pali_gemma/pali_gemma_inference.py
sinapsis_huggingface_transformers/thirdparty/__init__.py
sinapsis_huggingface_transformers/thirdparty/helpers.py
sinapsis_huggingface_transformers-0.2.13.dist-info/licenses/LICENSE
sinapsis_huggingface_transformers-0.2.13.dist-info/METADATA
sinapsis_huggingface_transformers-0.2.13.dist-info/WHEEL
sinapsis_huggingface_transformers-0.2.13.dist-info/top_level.txt
sinapsis_huggingface_transformers-0.2.13.dist-info/RECORD
