Metadata-Version: 2.4
Name: sinapsis-huggingface-transformers
Version: 0.2.13
Summary: Templates for HuggingFace Transformers, supporting automatic-speech-recognition, text-to-speech, translation and summarization templates
Author-email: SinapsisAI <dev@sinapsis.tech>
Project-URL: Homepage, https://sinapsis.tech
Project-URL: Documentation, https://docs.sinapsis.tech/docs
Project-URL: Tutorials, https://docs.sinapsis.tech/tutorials
Project-URL: Repository, https://github.com/Sinapsis-AI/sinapsis-huggingface.git
Requires-Python: >=3.10
License-File: LICENSE
Requires-Dist: accelerate>=1.1.1
Requires-Dist: clang>=17.0.6
Requires-Dist: flax>=0.7.1
Requires-Dist: peft>=0.14.0
Requires-Dist: sentencepiece>=0.2.0
Requires-Dist: sinapsis>=0.1.1
Requires-Dist: soundfile>=0.13.1
Requires-Dist: torch>=2.5.1
Requires-Dist: transformers>=4.47.1
Dynamic: license-file
